django_cloud_thumbnails/__init__.py
django_cloud_thumbnails/admin.py
django_cloud_thumbnails/config.py
django_cloud_thumbnails/fields.py
django_cloud_thumbnails/utils.py
django_cloud_thumbnails/widgets.py
django_cloud_thumbnails/backends/__init__.py
django_cloud_thumbnails/backends/base.py
django_cloud_thumbnails/backends/cloud_thumbnails.py
django_cloud_thumbnails/static/django_cloud_thumbnails/css/Jcrop.gif
django_cloud_thumbnails/static/django_cloud_thumbnails/css/image_cropping.css
django_cloud_thumbnails/static/django_cloud_thumbnails/css/jquery.Jcrop.css
django_cloud_thumbnails/static/django_cloud_thumbnails/css/jquery.Jcrop.min.css
django_cloud_thumbnails/static/django_cloud_thumbnails/js/dist/image_cropping.min.js
django_cloud_thumbnails/static/django_cloud_thumbnails/js/src/image_cropping.js
django_cloud_thumbnails/static/django_cloud_thumbnails/js/src/jquery.Jcrop.min.js
django_cloud_thumbnails/templatetags/__init__.py
django_cloud_thumbnails/templatetags/cropping.py
django_cloud_thumbnails-1.2.3.dist-info/LICENSE
django_cloud_thumbnails-1.2.3.dist-info/METADATA
django_cloud_thumbnails-1.2.3.dist-info/WHEEL
django_cloud_thumbnails-1.2.3.dist-info/top_level.txt
django_cloud_thumbnails-1.2.3.dist-info/RECORD
