Metadata-Version: 2.1
Name: django-cloud-thumbnails
Version: 1.2.3
Summary: Django Cloud Thumbnails is a fork of django-image-cropping that uses django-cloud-storage, a custom Django storage backend.
Author-email: cybermeh <cybermeh@icloud.com>
Classifier: Environment :: Web Environment
Classifier: Framework :: Django
Classifier: Framework :: Django :: 4.2
Classifier: Intended Audience :: Developers
Classifier: License :: OSI Approved :: BSD License
Classifier: Operating System :: OS Independent
Classifier: Programming Language :: Python
Classifier: Programming Language :: Python :: 3
Classifier: Programming Language :: Python :: 3 :: Only
Classifier: Programming Language :: Python :: 3.8
Classifier: Programming Language :: Python :: 3.9
Classifier: Topic :: Internet :: WWW/HTTP
Classifier: Topic :: Internet :: WWW/HTTP :: Dynamic Content
Requires-Python: >=3.10
License-File: LICENSE
Requires-Dist: Django >=4.2
Requires-Dist: pillow >=10.2.0
Requires-Dist: django-cloud-storage >=1.0.4
Requires-Dist: django-appconf >=1.0.2
